README.md
setup.cfg
setup.py
dattasa/__init__.py
dattasa/dag_controller.py
dattasa/data_pipeline.py
dattasa/delighted_client.py
dattasa/environment.py
dattasa/file_processor.py
dattasa/kafka_system.py
dattasa/mixpanel_client.py
dattasa/mongo_client.py
dattasa/mysql_client.py
dattasa/notifications.py
dattasa/postgres_client.py
dattasa/rabbitmq_system.py
dattasa/redis_client.py
dattasa/salesforce_client.py
dattasa/wootric_client.py
dattasa.egg-info/PKG-INFO
dattasa.egg-info/SOURCES.txt
dattasa.egg-info/dependency_links.txt
dattasa.egg-info/requires.txt
dattasa.egg-info/top_level.txt