Metadata-Version: 1.1
Name: dattasa
Version: 1.1
Summary: Python wrapper for connecting to postgres/greenplum, mysql, mongodb, kafka, redis, mixpanel and salesforce.        Also included are modules for performing secure file transfer and sourcing environment variables.
Home-page: https://github.com/kartikra/dattasa
Author: Kartik Ramasubramanian
Author-email: r.kartik@berkeley.edu
License: GNU
Keywords: greenplum postgres mysql mongodb kafka redis rabbitmq salesforce mixpanel delighted wootric data pipeline
Platform: UNKNOWN
Classifier: Development Status :: 4 - Beta
Classifier: License :: OSI Approved :: MIT License
Classifier: Programming Language :: Python :: 2
Classifier: Programming Language :: Python :: 2.7
Classifier: Programming Language :: Python :: 3
Classifier: Programming Language :: Python :: 3.3
Classifier: Programming Language :: Python :: 3.4
Classifier: Programming Language :: Python :: 3.5
Classifier: Programming Language :: Python :: 3.6
